[
    {
        "name": "realestate\\ownership\\Owner",
        "lang": "fr",
        "data": [
            {
                "id": 1,
                "condo_id": 1,
                "ownership_id": 2,
                "owner_shares": 100,
                "owner_type": "full",
                "identity_id": 10
            },
            {
                "id": 2,
                "condo_id": 1,
                "ownership_id": 3,
                "owner_shares": 100,
                "owner_type": "full",
                "identity_id": 6
            },
            {
                "id": 3,
                "condo_id": 1,
                "ownership_id": 4,
                "owner_shares": 100,
                "owner_type": "usufruct",
                "identity_id": 4
            },
            {
                "id": 4,
                "condo_id": 2,
                "ownership_id": 5,
                "owner_shares": 100,
                "owner_type": "full",
                "identity_id": 7
            },
            {
                "id": 5,
                "condo_id": 2,
                "ownership_id": 6,
                "owner_shares": 100,
                "owner_type": "full",
                "identity_id": 5
            },
            {
                "id": 6,
                "condo_id": 2,
                "ownership_id": 7,
                "owner_shares": 100,
                "owner_type": "full",
                "identity_id": 3
            },
            {
                "id": 7,
                "condo_id": 1,
                "ownership_id": 4,
                "owner_shares": 50,
                "owner_type": "bare",
                "identity_id": 8
            },
            {
                "id": 8,
                "condo_id": 1,
                "ownership_id": 4,
                "owner_shares": 50,
                "owner_type": "bare",
                "identity_id": 9
            }
        ]
    }
]